apertools/__init__.py
apertools/asfdownload.py
apertools/colors.py
apertools/constants.py
apertools/correlation.py
apertools/coseismic_stack.py
apertools/createdem.py
apertools/demloading.py
apertools/deramp.py
apertools/geocode.py
apertools/geojson.py
apertools/gps.py
apertools/gps_plots.py
apertools/isce_helpers.py
apertools/kml.py
apertools/ks.py
apertools/latlon.py
apertools/log.py
apertools/los.py
apertools/netcdf.py
apertools/parsers.py
apertools/pct_zeros.c
apertools/plotting.py
apertools/sario.py
apertools/stitching.py
apertools/subset.py
apertools/utils.py
apertools/data/asfquery_platform_beammodes.csv
apertools/data/asfquery_platform_processinglevels.csv
apertools/data/asfquery_platforms.csv
apertools/data/station_llh_all.csv
apertools/data/station_xyz_all.csv
apertools/scripts/__init__.py
apertools/scripts/cli.py
apertools/scripts/gdalcopyproj.py
apertools/scripts/hdf5_geotiff.py
apertools/scripts/run_geocode.py
apertools/tests/__init__.py
apertools/tests/test_geojson.py
apertools/tests/test_parsers.py
apertools/tests/test_sario.py
apertools/tests/test_stitching.py
apertools/tests/test_utils.py
apertools/tests/data/20180420_20180422.unw
apertools/tests/data/20180420_20180428.unw
apertools/tests/data/20180422_20180428.unw
apertools/tests/data/20180422_20180502.unw
apertools/tests/data/20180428_20180502.unw
apertools/tests/data/S1A_IW_SLC__1SDV_20180420T043026_20180420T043054_021546_025211_81BE.SAFE.small.geo
apertools/tests/data/brazos_14937_17090_017_170903_L090_CX_01.ann
apertools/tests/data/elevation.dem
apertools/tests/data/elevation.dem.rsc
apertools/tests/data/sbas_test/20180420_20180422.unw
apertools/tests/data/sbas_test/20180420_20180428.unw
apertools/tests/data/sbas_test/20180422_20180428.unw
apertools/tests/data/sbas_test/20180422_20180502.unw
apertools/tests/data/sbas_test/20180428_20180502.unw
apertools/tests/data/sbas_test/README.md
apertools/tests/data/sbas_test/dem.rsc
apertools/tests/data/sbas_test/geolist
apertools-0.7.0.dist-info/LICENSE.txt
apertools-0.7.0.dist-info/METADATA
apertools-0.7.0.dist-info/WHEEL
apertools-0.7.0.dist-info/entry_points.txt
apertools-0.7.0.dist-info/top_level.txt
apertools-0.7.0.dist-info/RECORD
