Metadata-Version: 2.1
Name: apertools
Version: 0.7.0
Summary: Tools for gathering and processing InSAR data
Home-page: https://github.com/scottstanie/apertools
Author: Scott Staniewicz
Author-email: scott.stanie@utexas.com
License: UNKNOWN
Platform: UNKNOWN
Classifier: Programming Language :: Python
Classifier: Programming Language :: Python :: 2.7
Classifier: Programming Language :: Python :: 3.3
Classifier: Programming Language :: Python :: 3.4
Classifier: Programming Language :: Python :: 3.5
Classifier: Programming Language :: Python :: 3.6
Classifier: Programming Language :: C
Classifier: License :: OSI Approved :: MIT License
Classifier: Topic :: Scientific/Engineering
Classifier: Intended Audience :: Science/Research
Requires-Dist: numpy
Requires-Dist: requests
Requires-Dist: matplotlib
Requires-Dist: click
Requires-Dist: h5py
Requires-Dist: sentineleof
